{
  "stops": [
    {
      "city": "Athens",
      "departureAt": "2027-03-01T00:00:00Z",
      "travelers": [
        "traveler-1",
        "traveler-2",
        "traveler-3"
      ]
    },
    {
      "arrivalAt": "2027-03-01T03:00:00Z",
      "city": "Berlin",
      "departureAt": "2027-03-01T08:00:00Z",
      "travelers": [
        "traveler-1",
        "traveler-2",
        "traveler-3"
      ]
    },
    {
      "arrivalAt": "2027-03-01T11:00:00Z",
      "city": "Rome",
      "departureAt": "2027-03-01T16:00:00Z",
      "travelers": [
        "traveler-1",
        "traveler-2",
        "traveler-3"
      ]
    },
    {
      "arrivalAt": "2027-03-01T19:00:00Z",
      "city": "Moscow",
      "departureAt": "2027-03-02T00:00:00Z",
      "travelers": [
        "traveler-1",
        "traveler-2",
        "traveler-3"
      ]
    },
    {
      "arrivalAt": "2027-03-02T03:00:00Z",
      "city": "Amsterdam",
      "departureAt": "2027-03-02T08:00:00Z",
      "travelers": [
        "traveler-1",
        "traveler-2",
        "traveler-3"
      ]
    },
    {
      "arrivalAt": "2027-03-02T11:00:00Z",
      "city": "Berlin",
      "departureAt": "2027-03-02T16:00:00Z",
      "travelers": [
        "traveler-1",
        "traveler-2",
        "traveler-3"
      ]
    },
    {
      "arrivalAt": "2027-03-02T19:00:00Z",
      "city": "Athens",
      "travelers": [
        "traveler-1",
        "traveler-2",
        "traveler-3"
      ]
    }
  ],
  "transits": [
    {
      "arrivalAt": "2027-03-01T03:00:00Z",
      "departureAt": "2027-03-01T00:00:00Z",
      "from": "Athens",
      "mode": "rail",
      "sourceFragmentId": "107-circle-3p-seeded-shuffle-return-tkt-01",
      "to": "Berlin",
      "travelers": [
        "traveler-1",
        "traveler-2",
        "traveler-3"
      ]
    },
    {
      "arrivalAt": "2027-03-01T11:00:00Z",
      "departureAt": "2027-03-01T08:00:00Z",
      "from": "Berlin",
      "mode": "rail",
      "sourceFragmentId": "107-circle-3p-seeded-shuffle-return-tkt-01",
      "to": "Rome",
      "travelers": [
        "traveler-1",
        "traveler-2",
        "traveler-3"
      ]
    },
    {
      "arrivalAt": "2027-03-01T19:00:00Z",
      "departureAt": "2027-03-01T16:00:00Z",
      "from": "Rome",
      "mode": "rail",
      "sourceFragmentId": "107-circle-3p-seeded-shuffle-return-tkt-01",
      "to": "Moscow",
      "travelers": [
        "traveler-1",
        "traveler-2",
        "traveler-3"
      ]
    },
    {
      "arrivalAt": "2027-03-02T03:00:00Z",
      "departureAt": "2027-03-02T00:00:00Z",
      "from": "Moscow",
      "mode": "bus",
      "sourceFragmentId": "107-circle-3p-seeded-shuffle-return-tkt-02",
      "to": "Amsterdam",
      "travelers": [
        "traveler-1",
        "traveler-2",
        "traveler-3"
      ]
    },
    {
      "arrivalAt": "2027-03-02T11:00:00Z",
      "departureAt": "2027-03-02T08:00:00Z",
      "from": "Amsterdam",
      "mode": "rail",
      "sourceFragmentId": "107-circle-3p-seeded-shuffle-return-tkt-03",
      "to": "Berlin",
      "travelers": [
        "traveler-1",
        "traveler-2",
        "traveler-3"
      ]
    },
    {
      "arrivalAt": "2027-03-02T19:00:00Z",
      "departureAt": "2027-03-02T16:00:00Z",
      "from": "Berlin",
      "mode": "rail",
      "sourceFragmentId": "107-circle-3p-seeded-shuffle-return-tkt-03",
      "to": "Athens",
      "travelers": [
        "traveler-1",
        "traveler-2",
        "traveler-3"
      ]
    }
  ],
  "travelers": [
    "traveler-1",
    "traveler-2",
    "traveler-3"
  ]
}
