{
  "stops": [
    {
      "city": "LHR",
      "departureAt": "2027-03-01T00:00:00Z",
      "travelers": [
        "traveler-1"
      ]
    },
    {
      "accommodations": [
        {
          "checkInAt": "2027-03-01T03:00:00Z",
          "checkOutAt": "2027-03-01T21:00:00Z",
          "hotelName": "Riverside Inn"
        }
      ],
      "arrivalAt": "2027-03-01T03:00:00Z",
      "city": "BER",
      "departureAt": "2027-03-01T21:00:00Z",
      "travelers": [
        "traveler-1"
      ]
    },
    {
      "accommodations": [
        {
          "checkInAt": "2027-03-02T00:00:00Z",
          "checkOutAt": "2027-03-02T18:00:00Z",
          "hotelName": "Old Town Hostel"
        }
      ],
      "arrivalAt": "2027-03-02T00:00:00Z",
      "city": "ZRH",
      "departureAt": "2027-03-02T18:00:00Z",
      "travelers": [
        "traveler-1"
      ]
    },
    {
      "accommodations": [
        {
          "checkInAt": "2027-03-02T21:00:00Z",
          "checkOutAt": "2027-03-03T15:00:00Z",
          "hotelName": "Plaza Suites"
        }
      ],
      "arrivalAt": "2027-03-02T21:00:00Z",
      "city": "SVO",
      "departureAt": "2027-03-03T15:00:00Z",
      "travelers": [
        "traveler-1"
      ]
    },
    {
      "accommodations": [
        {
          "checkInAt": "2027-03-03T18:00:00Z",
          "checkOutAt": "2027-03-04T12:00:00Z",
          "hotelName": "Central Lodge"
        }
      ],
      "arrivalAt": "2027-03-03T18:00:00Z",
      "city": "ROM",
      "departureAt": "2027-03-04T12:00:00Z",
      "travelers": [
        "traveler-1"
      ]
    },
    {
      "arrivalAt": "2027-03-04T15:00:00Z",
      "city": "BER",
      "travelers": [
        "traveler-1"
      ]
    }
  ],
  "transits": [
    {
      "arrivalAt": "2027-03-01T03:00:00Z",
      "departureAt": "2027-03-01T00:00:00Z",
      "from": "LHR",
      "mode": "rail",
      "sourceFragmentId": "071-circle-1p-seeded-shuffle-hotels-tkt-01",
      "to": "BER",
      "travelers": [
        "traveler-1"
      ]
    },
    {
      "arrivalAt": "2027-03-02T00:00:00Z",
      "departureAt": "2027-03-01T21:00:00Z",
      "from": "BER",
      "mode": "rail",
      "sourceFragmentId": "071-circle-1p-seeded-shuffle-hotels-tkt-01",
      "to": "ZRH",
      "travelers": [
        "traveler-1"
      ]
    },
    {
      "arrivalAt": "2027-03-02T21:00:00Z",
      "departureAt": "2027-03-02T18:00:00Z",
      "from": "ZRH",
      "mode": "rail",
      "sourceFragmentId": "071-circle-1p-seeded-shuffle-hotels-tkt-01",
      "to": "SVO",
      "travelers": [
        "traveler-1"
      ]
    },
    {
      "arrivalAt": "2027-03-03T18:00:00Z",
      "departureAt": "2027-03-03T15:00:00Z",
      "from": "SVO",
      "mode": "bus",
      "sourceFragmentId": "071-circle-1p-seeded-shuffle-hotels-tkt-02",
      "to": "ROM",
      "travelers": [
        "traveler-1"
      ]
    },
    {
      "arrivalAt": "2027-03-04T15:00:00Z",
      "departureAt": "2027-03-04T12:00:00Z",
      "from": "ROM",
      "mode": "rail",
      "sourceFragmentId": "071-circle-1p-seeded-shuffle-hotels-tkt-03",
      "to": "BER",
      "travelers": [
        "traveler-1"
      ]
    }
  ],
  "travelers": [
    "traveler-1"
  ]
}
