{
  "cities": [
    "Stockholm",
    "Helsinki",
    "Paris",
    "Rome"
  ],
  "documentType": "rail-ticket",
  "pnr": "PNR001068",
  "sourceDocumentId": "068-circle-1p-forward-hotels-tkt-01",
  "stations": [
    {
      "city": "Stockholm",
      "departureAt": "2027-03-01T00:00:00Z",
      "identifier": "Stockholm Hauptbahnhof",
      "kind": "rail_station"
    },
    {
      "arrivalAt": "2027-03-01T03:00:00Z",
      "city": "Helsinki",
      "departureAt": "2027-03-01T21:00:00Z",
      "identifier": "Helsinki Hauptbahnhof",
      "kind": "rail_station"
    },
    {
      "arrivalAt": "2027-03-02T00:00:00Z",
      "city": "Paris",
      "departureAt": "2027-03-02T18:00:00Z",
      "identifier": "Paris Hauptbahnhof",
      "kind": "rail_station"
    },
    {
      "arrivalAt": "2027-03-02T21:00:00Z",
      "city": "Rome",
      "identifier": "Rome Hauptbahnhof",
      "kind": "rail_station"
    }
  ],
  "travelers": [
    "traveler-1"
  ]
}
