{
  "cities": [
    "Copenhagen",
    "New York"
  ],
  "documentType": "rail-ticket",
  "pnr": "PNR002132",
  "sourceDocumentId": "132-star-1p-forward-hotels-tkt-02",
  "stations": [
    {
      "city": "Copenhagen",
      "departureAt": "2027-03-03T15:00:00Z",
      "identifier": "Copenhagen Hauptbahnhof",
      "kind": "rail_station"
    },
    {
      "arrivalAt": "2027-03-03T18:00:00Z",
      "city": "New York",
      "identifier": "New York Hauptbahnhof",
      "kind": "rail_station"
    }
  ],
  "travelers": [
    "traveler-1"
  ]
}
