{
  "cities": [
    "Istanbul",
    "Vienna",
    "Helsinki",
    "Stockholm"
  ],
  "documentType": "bus-ticket",
  "pnr": "PNR001091",
  "sourceDocumentId": "091-circle-2p-seeded-shuffle-return-tkt-01",
  "stations": [
    {
      "city": "Istanbul",
      "departureAt": "2027-03-01T00:00:00Z",
      "identifier": "Istanbul Bus Terminal",
      "kind": "bus_terminal"
    },
    {
      "arrivalAt": "2027-03-01T03:00:00Z",
      "city": "Vienna",
      "departureAt": "2027-03-01T08:00:00Z",
      "identifier": "Vienna Bus Terminal",
      "kind": "bus_terminal"
    },
    {
      "arrivalAt": "2027-03-01T11:00:00Z",
      "city": "Helsinki",
      "departureAt": "2027-03-01T16:00:00Z",
      "identifier": "Helsinki Bus Terminal",
      "kind": "bus_terminal"
    },
    {
      "arrivalAt": "2027-03-01T19:00:00Z",
      "city": "Stockholm",
      "identifier": "Stockholm Bus Terminal",
      "kind": "bus_terminal"
    }
  ],
  "travelers": [
    "traveler-1",
    "traveler-2"
  ]
}
