{
  "stops": [
    {
      "city": "WAW",
      "departureAt": "2027-03-01T00:00:00Z",
      "travelers": [
        "traveler-1"
      ]
    },
    {
      "accommodations": [
        {
          "checkInAt": "2027-03-01T03:00:00Z",
          "checkOutAt": "2027-03-01T21:00:00Z",
          "hotelName": "Riverside Inn"
        }
      ],
      "arrivalAt": "2027-03-01T03:00:00Z",
      "city": "CDG",
      "departureAt": "2027-03-01T21:00:00Z",
      "travelers": [
        "traveler-1"
      ]
    },
    {
      "accommodations": [
        {
          "checkInAt": "2027-03-02T00:00:00Z",
          "checkOutAt": "2027-03-02T18:00:00Z",
          "hotelName": "Old Town Hostel"
        }
      ],
      "arrivalAt": "2027-03-02T00:00:00Z",
      "city": "FRA",
      "departureAt": "2027-03-02T18:00:00Z",
      "travelers": [
        "traveler-1"
      ]
    },
    {
      "arrivalAt": "2027-03-02T21:00:00Z",
      "city": "MAD",
      "travelers": [
        "traveler-1"
      ]
    }
  ],
  "transits": [
    {
      "arrivalAt": "2027-03-01T03:00:00Z",
      "departureAt": "2027-03-01T00:00:00Z",
      "from": "WAW",
      "mode": "bus",
      "sourceFragmentId": "007-straight-1p-seeded-shuffle-hotels-tkt-01",
      "to": "CDG",
      "travelers": [
        "traveler-1"
      ]
    },
    {
      "arrivalAt": "2027-03-02T00:00:00Z",
      "departureAt": "2027-03-01T21:00:00Z",
      "from": "CDG",
      "mode": "bus",
      "sourceFragmentId": "007-straight-1p-seeded-shuffle-hotels-tkt-01",
      "to": "FRA",
      "travelers": [
        "traveler-1"
      ]
    },
    {
      "arrivalAt": "2027-03-02T21:00:00Z",
      "departureAt": "2027-03-02T18:00:00Z",
      "from": "FRA",
      "mode": "bus",
      "sourceFragmentId": "007-straight-1p-seeded-shuffle-hotels-tkt-01",
      "to": "MAD",
      "travelers": [
        "traveler-1"
      ]
    }
  ],
  "travelers": [
    "traveler-1"
  ]
}
