{
  "documentType": "bus-ticket",
  "legs": [
    {
      "arrivalAt": "2027-03-01T03:00:00Z",
      "carrier": "FlixBus",
      "departureAt": "2027-03-01T00:00:00Z",
      "from": "Zurich",
      "to": "Athens",
      "vehicleNumber": "FL100"
    },
    {
      "arrivalAt": "2027-03-01T11:00:00Z",
      "carrier": "FlixBus",
      "departureAt": "2027-03-01T08:00:00Z",
      "from": "Athens",
      "to": "Stockholm",
      "vehicleNumber": "FL101"
    },
    {
      "arrivalAt": "2027-03-01T19:00:00Z",
      "carrier": "FlixBus",
      "departureAt": "2027-03-01T16:00:00Z",
      "from": "Stockholm",
      "to": "Moscow",
      "vehicleNumber": "FL102"
    }
  ],
  "pnr": "PNR001001",
  "sourceDocumentId": "001-straight-1p-reverse-tkt-01",
  "travelers": [
    "traveler-1"
  ]
}
